poolguy/__init__.py
poolguy/http.py
poolguy/oauth.py
poolguy/storage.py
poolguy/twitch.py
poolguy/twitchapi.py
poolguy/twitchws.py
poolguy/webserver.py
poolguy-0.1.8.dist-info/licenses/LICENSE
poolguy-0.1.8.dist-info/METADATA
poolguy-0.1.8.dist-info/WHEEL
poolguy-0.1.8.dist-info/top_level.txt
poolguy-0.1.8.dist-info/RECORD
