Metadata-Version: 2.4
Name: poolguy
Version: 0.1.8
Summary: A Twitch bot framework with event subscription and alert handling capabilities
Home-page: https://github.com/s4w3d0ff/pool-guy
Author: s4w3d0ff
Author-email: 
License: GNU General Public License v3 (GPLv3)
Keywords: twitch,bot,eventsub,websocket,async,alerts,streaming,poolguy
Platform: any
Classifier: Development Status :: 3 - Alpha
Classifier: Programming Language :: Python :: 3
Classifier: License :: OSI Approved :: GNU General Public License v3 (GPLv3)
Classifier: Operating System :: OS Independent
Classifier: Topic :: Internet :: WWW/HTTP :: Dynamic Content
Classifier: Topic :: Communications :: Chat
Classifier: Framework :: AsyncIO
Requires-Python: >=3.10
License-File: LICENSE
Requires-Dist: aiohttp
Requires-Dist: websockets
Requires-Dist: python-dateutil
Requires-Dist: aiofiles
Provides-Extra: mongodb
Requires-Dist: pymongo; extra == "mongodb"
Provides-Extra: sqlite
Requires-Dist: aiosqlite; extra == "sqlite"
Dynamic: author
Dynamic: classifier
Dynamic: description
Dynamic: description-content-type
Dynamic: home-page
Dynamic: keywords
Dynamic: license
Dynamic: license-file
Dynamic: platform
Dynamic: provides-extra
Dynamic: requires-dist
Dynamic: requires-python
Dynamic: summary
